LICENSE
README.md
setup.py
fouryousee/__init__.py
fouryousee/fouryousee.py
fouryousee.egg-info/PKG-INFO
fouryousee.egg-info/SOURCES.txt
fouryousee.egg-info/dependency_links.txt
fouryousee.egg-info/not-zip-safe
fouryousee.egg-info/requires.txt
fouryousee.egg-info/top_level.txt